{
  "versionCur": "v0.2.5",
  "v0.2.5": {
    "date": "2021-3-24",
    "type": "",
    "desc": "<b>新特性：</b><br>1.增加文章《聆听的十条原则》<br> 2.增加文章《有效倾听的障碍》<br>3.增加文章《有效的倾听技巧》<br>4.修改文章的侧边栏<br>5.修改首页文章的样式<br><b>修复bug：1.修复连续点击倾听技巧会出现404的问题</b>"
  },
  "v0.2.4": {  
    "date": "2021-3-14",
    "type": "",
    "desc": "<b>新特性：</b><br><br><b>修复bug：1.markdown内的一些超链接<br>2.修复有效倾听重要提示的侧边栏展示错误问题</b>"
  },
  "v0.2.3": {
    "date": "2021-3-13",
    "type": "",
    "desc": "<b>新特性：</b><br>1.修改首页文字大小<br> 2.开始测试功能<br>3.修改文章标题字体大小<br>4.修改文章背景颜色<br><b>修复bug：1.侧边栏看不到箭头</b>"
  },
  "v0.2.2": {
    "date": "2021-3-6",
    "type": "",
    "desc": "<b>新特性：</b><br>1.修改首页图标大小<br><b>修复bug：</b><br>1.修复一些文章跳转的问题"
  },
  "v0.2.1": {
    "date": "2021-2-28",
    "type": "",
    "desc": "<b>新特性：</b><br>1.增加文章《倾听技巧》<br><b>修复bug：</b><br>1.修复一些文章跳转的问题"
  },
  "v0.2.0": {
    "date": "2021-2-27",
    "type": "",
    "desc": "<b>新特性：</b><br>1.修改布局<br>2.增加文章《有效倾听的重要提示》<br>"
  },
  "v0.1.4": {
    "date": "2021-2-15",
    "type": "",
    "desc": "<b>新特性：</b><br>1.修改标题内容<br><b>修复bug：</b><br>1.删除了一些冗余文件"
  },
  "v0.1.3": {
    "date": "2021-2-14",
    "type": "",
    "desc": "<b>新特性：</b><br>1.增加情商的侧边栏<br><b>修复bug：</b><br>1.修复情商原本没有全局组件的问题 <br>2.修复首页跳转到未知页面的问题<br>3.修改了主页路径"
  },
  "v0.1.2": {
    "date": "2021-2-13",
    "type": "",
    "desc": "<b>新特性：</b><br>1.增加文章的导航<br>2.更新了一些图标<br>3.修改了一些文章格式<b>"
  },
  "v0.1.1": {
    "date": "2021-2-11",
    "type": "",
    "desc": "<b>新特性：</b><br>1.增加文章《言语交流》<br>2.增加文章《交流技能》<br>3.增加底部栏<br><b>修复bug：</b><br>1.导航栏导航功能恢复 <br>2.修改了页面内容不足时页面过小的问题<br>3.修复了顶部导航栏文字偏低问题"
  },
  "v0.1.0": {
    "date": "2021-2-10",
    "type": "",
    "desc": "<b>新特性：</b><br>1.增加文章《倾听技巧》<br>2.增加文章《什么是沟通》<br>3.增加文章《非口头交流》<br>4.增加文章《人际沟通技巧》<br>5.增加文章《有效人际沟通的技巧》<br>6.增加段落缩进<br>7. 修改了路由<br>8.修改侧边栏出现方式<br><b>修复bug：</b><br>1.每页自设置导航栏 <br>2.更改主页文章<br>3.修复404页面无法返回首页的问题"
  },
  "v0.0.6": {
    "date": "2021-2-9",
    "type": "",
    "desc": "<b>新特性：</b><br>1.增加404页面<br>2.增加了无路由时导航至404页面的功能"
  },
  "v0.0.5": {
    "date": "2021-2-8",
    "type": "",
    "desc": "<b>新特性：</b><br>1.增加了文章《情商》<br>2.增加了侧边栏的导航功能"
  },
  "v0.0.4": {
    "date": "2021-2-7",
    "type": "",
    "desc": "<b>新特性：</b><br>1.更改了侧边栏、主要内容的颜色"
  },
  "v0.0.3": {
    "date": "2021-2-6",
    "type": "",
    "desc": "<b>新特性：</b><br>1.增加侧边栏<br>2.增加layout文件夹放置布局<br>3.修改了侧边栏文字样式<br>4.增加了iconfont的图标"
  },
  "v0.0.2": {
    "date": "2021-1-30",
    "type": "",
    "desc": "<b>新特性：</b><br>1.切换成vue2<br>2.增加渲染markdown的功能<br>3.增加logo图片跳转回首页的功能"
  },
  "v0.0.1": {
    "date": "2022-1-29",
    "type": "",
    "desc": "<b>新特性：</b><br>1.创建项目<br>2.设计首页上方头部<br>3.增加logo图片"
  }
}
